MANIFEST.in
setup.cfg
setup.py
libacr/__init__.py
libacr/form_fields.py
libacr/forms.py
libacr/helpers.py
libacr/lib.py
libacr/migrations.py
libacr/rss.py
libacr/unicodecfp.py
libacr.egg-info/PKG-INFO
libacr.egg-info/SOURCES.txt
libacr.egg-info/dependency_links.txt
libacr.egg-info/entry_points.txt
libacr.egg-info/not-zip-safe
libacr.egg-info/requires.txt
libacr.egg-info/top_level.txt
libacr/contrib/__init__.py
libacr/contrib/tinymce/__init__.py
libacr/contrib/tinymce/widgets.py
libacr/contrib/tinymce/static/javascript/jquery.tinymce.js
libacr/contrib/tinymce/static/javascript/tiny_mce.js
libacr/contrib/tinymce/static/javascript/tiny_mce_dev.js
libacr/contrib/tinymce/static/javascript/tiny_mce_jquery.js
libacr/contrib/tinymce/static/javascript/tiny_mce_jquery_src.js
libacr/contrib/tinymce/static/javascript/tiny_mce_popup.js
libacr/contrib/tinymce/static/javascript/tiny_mce_prototype.js
libacr/contrib/tinymce/static/javascript/tiny_mce_prototype_src.js
libacr/contrib/tinymce/static/javascript/tiny_mce_src.js
libacr/contrib/tinymce/static/javascript/langs/ar.js
libacr/contrib/tinymce/static/javascript/langs/az.js
libacr/contrib/tinymce/static/javascript/langs/be.js
libacr/contrib/tinymce/static/javascript/langs/bg.js
libacr/contrib/tinymce/static/javascript/langs/bn.js
libacr/contrib/tinymce/static/javascript/langs/br.js
libacr/contrib/tinymce/static/javascript/langs/bs.js
libacr/contrib/tinymce/static/javascript/langs/ca.js
libacr/contrib/tinymce/static/javascript/langs/ch.js
libacr/contrib/tinymce/static/javascript/langs/cs.js
libacr/contrib/tinymce/static/javascript/langs/cy.js
libacr/contrib/tinymce/static/javascript/langs/da.js
libacr/contrib/tinymce/static/javascript/langs/de.js
libacr/contrib/tinymce/static/javascript/langs/dv.js
libacr/contrib/tinymce/static/javascript/langs/el.js
libacr/contrib/tinymce/static/javascript/langs/en.js
libacr/contrib/tinymce/static/javascript/langs/es.js
libacr/contrib/tinymce/static/javascript/langs/et.js
libacr/contrib/tinymce/static/javascript/langs/eu.js
libacr/contrib/tinymce/static/javascript/langs/fa.js
libacr/contrib/tinymce/static/javascript/langs/fi.js
libacr/contrib/tinymce/static/javascript/langs/fr.js
