Metadata-Version: 1.0
Name: libacr
Version: 0.7.7
Summary: TurboGears2 Content Management Framework
Home-page: http://www.acrcms.org
Author: AXANT
Author-email: acr@axantlabs.com
License: LGPL
Keywords: turbogears2.extension cms cmf web
Platform: UNKNOWN
Classifier: Development Status :: 4 - Beta
Classifier: Environment :: Web Environment
Classifier: Framework :: TurboGears
Classifier: License :: OSI Approved :: GNU General Public License (GPL)
Classifier: Operating System :: OS Independent
Classifier: Programming Language :: Python
Classifier: Topic :: Internet :: WWW/HTTP :: Dynamic Content
Classifier: Topic :: Software Development :: Libraries :: Python Modules
